pdl/__init__.py
pdl/_version.py
pdl/pdl-schema.json
pdl/pdl.py
pdl/pdl_analysis.py
pdl/pdl_ast.py
pdl/pdl_ast_utils.py
pdl/pdl_context.py
pdl/pdl_dumper.py
pdl/pdl_granite_io.py
pdl/pdl_interpreter.py
pdl/pdl_interpreter_state.py
pdl/pdl_lazy.py
pdl/pdl_linter.py
pdl/pdl_llms.py
pdl/pdl_location_utils.py
pdl/pdl_notebook_ext.py
pdl/pdl_parser.py
pdl/pdl_python_repl.py
pdl/pdl_runner.py
pdl/pdl_scheduler.py
pdl/pdl_schema_error_analyzer.py
pdl/pdl_schema_utils.py
pdl/pdl_schema_validator.py
pdl/pdl_stdlib.pdl
pdl/pdl_stdlib.py
pdl/pdl_utils.py
pdl/optimize/__init__.py
pdl/optimize/config_parser.py
pdl/optimize/optimizer_evaluator.py
pdl/optimize/parse_number.py
pdl/optimize/pdl_evaluator.py
pdl/optimize/pdl_optimizer.py
pdl/optimize/util.py
pdl/pdl_compilers/__init__.py
pdl/pdl_compilers/to_regex.py
prompt_declaration_language-0.9.2.dist-info/licenses/LICENSE
prompt_declaration_language-0.9.2.dist-info/METADATA
prompt_declaration_language-0.9.2.dist-info/WHEEL
prompt_declaration_language-0.9.2.dist-info/entry_points.txt
prompt_declaration_language-0.9.2.dist-info/top_level.txt
prompt_declaration_language-0.9.2.dist-info/RECORD
