Metadata-Version: 2.4
Name: prompt-declaration-language
Version: 0.9.2
Summary: Prompt Declaration Language
Author-email: Mandana Vaziri <mvaziri@us.ibm.com>, Louis Mandel <lmandel@us.ibm.com>, Claudio Spiess <claudiosv@users.noreply.github.com>, Martin Hirzel <hirzel@us.ibm.com>
Project-URL: Homepage, https://ibm.github.io/prompt-declaration-language/
Project-URL: Documentation, https://ibm.github.io/prompt-declaration-language/tutorial/
Project-URL: Source, https://github.com/IBM/prompt-declaration-language
Project-URL: Repository, https://github.com/IBM/prompt-declaration-language
Project-URL: Issues, https://github.com/IBM/prompt-declaration-language/issues
Classifier: Programming Language :: Python :: 3
Classifier: License :: OSI Approved :: Apache Software License
Classifier: Operating System :: OS Independent
Requires-Python: >=3.11
License-File: LICENSE
Requires-Dist: pydantic~=2.0
Requires-Dist: requests~=2.0
Requires-Dist: python-dotenv~=1.0
Requires-Dist: jinja2~=3.0
Requires-Dist: PyYAML~=6.0
Requires-Dist: jsonschema~=4.0
Requires-Dist: litellm>=1.66.0
Requires-Dist: openai>=1.66.1
Requires-Dist: termcolor<4,>=2
Requires-Dist: ipython<10,>=8
Requires-Dist: json-repair~=0.35
Requires-Dist: granite-io<0.6,>=0.5
Provides-Extra: dev
Requires-Dist: pre-commit<5,>=3; extra == "dev"
Requires-Dist: pytest~=9.0; extra == "dev"
Requires-Dist: pydantic~=2.9; extra == "dev"
Provides-Extra: examples
Requires-Dist: pymilvus~=2.5; extra == "examples"
Requires-Dist: langchain~=0.3; extra == "examples"
Requires-Dist: langchain-community~=0.3; extra == "examples"
Requires-Dist: pypdf~=6.0; extra == "examples"
Requires-Dist: wikipedia~=1.0; extra == "examples"
Requires-Dist: textdistance~=4.0; extra == "examples"
Requires-Dist: datasets<5,>3; extra == "examples"
Requires-Dist: sympy~=1.0; extra == "examples"
Requires-Dist: scikit-learn<1.8.0,>=1.6.1; extra == "examples"
Requires-Dist: faiss-cpu<1.14,>=1.13; extra == "examples"
Requires-Dist: funcy>=2; extra == "examples"
Requires-Dist: evalplus>=0.3.1; extra == "examples"
Provides-Extra: docs
Requires-Dist: mkdocs~=1.0; extra == "docs"
Requires-Dist: mkdocstrings[python]~=0.0; extra == "docs"
Requires-Dist: mkdocs-material~=9.0; extra == "docs"
Requires-Dist: pymdown-extensions~=10.0; extra == "docs"
Provides-Extra: optimizer
Requires-Dist: rich>=14.0.0; extra == "optimizer"
Requires-Dist: evalplus>=0.3.1; extra == "optimizer"
Requires-Dist: duration_parser>=1.0.1; extra == "optimizer"
Requires-Dist: multiprocess~=0.70; extra == "optimizer"
Provides-Extra: all
Requires-Dist: prompt-declaration-language[dev,docs,examples,optimizer]; extra == "all"
Dynamic: license-file
